aoc_plumber/__init__.py
aoc_plumber/__main__.py
aoc_plumber/cli/.aocplumber.toml
aoc_plumber/cli/config.py
aoc_plumber/cli/consts.py
aoc_plumber/cli/logger.py
aoc_plumber/cli/models.py
aoc_plumber/cli/parse.py
aoc_plumber/cli/run_cli.py
aoc_plumber/cli/utils.py
aoc_plumber/iter/it.py
aoc_plumber/iter/iter.py
aoc_plumber-0.6.1.dist-info/METADATA
aoc_plumber-0.6.1.dist-info/WHEEL
aoc_plumber-0.6.1.dist-info/RECORD
