Metadata-Version: 2.4
Name: aoc-plumber
Version: 0.6.1
Author-email: Alex <noelalexandre66@gmail.com>
Requires-Python: <4.0,>=3.10
Requires-Dist: loguru>=0.7.3
Requires-Dist: pydantic>=2.12.5
Requires-Dist: requests>=2.32.3
Requires-Dist: tomli>=2.3.0
Provides-Extra: dev
Requires-Dist: pytest>=9.0.2; extra == 'dev'
